hilale/__init__.py
hilale/__main__.py
hilale/hilale.py
hilale-0.1.2.dist-info/LICENSE
hilale-0.1.2.dist-info/WHEEL
hilale-0.1.2.dist-info/METADATA
hilale-0.1.2.dist-info/RECORD
